{
   "jsontv" : {
      "programme" : [
         {
            "new" : null,
            "stop" : "1522589100",
            "desc" : {
               "da" : "Ditte Okman er tilbage som Henriette Honor\u00e9s medv\u00e6rt, og i dag handler det blandt andet om en mand, der har meldt sig ind i en \"gul\" fagforening, og derfor har t\u00e6nkt sig at blive ved med at arbejde, n\u00e5r hans kolleger strejker. Vi skal ogs\u00e5 med til rollerderby i Aalborg med nogle rigtigt seje kvinder."
            },
            "start" : "1522587300",
            "channel" : "tv2nord.dk",
            "category" : {
               "en" : [
                  "series",
                  "Series"
               ]
            },
            "title" : {
               "da" : "S\u00e5danmark"
            }
         },
         {
            "category" : {
               "en" : [
                  "series",
                  "Series"
               ]
            },
            "episodeNum" : {
               "onscreen" : "Afsnit 13 af 52",
               "xmltv_ns" : ". 12/52 ."
            },
            "channel" : "tv2nord.dk",
            "stop" : "1522590900",
            "title" : {
               "da" : "Nationalpark Thy"
            },
            "desc" : {
               "da" : "Bliv inspireret til at komme ud i den frie luft og opleve Nationalpark Thy's storsl\u00e5ede natur. Afbr\u00e6ndinger giver nyt liv p\u00e5 klitheden. De nye levesteder giver st\u00f8rre artsrigdom i hele Nationalparken. Tilrettel\u00e6ggelse: Rigmor Sams"
            },
            "start" : "1522589100",
            "new" : null
         },
         {
            "category" : {
               "en" : [
                  "series",
                  "Series"
               ]
            },
            "episodeNum" : {
               "xmltv_ns" : ". 0/2 .",
               "onscreen" : "Afsnit 1 af 2"
            },
            "channel" : "tv2nord.dk",
            "stop" : "1522592700",
            "title" : {
               "da" : "Historisk Rally Monte Carlo"
            },
            "start" : "1522590900",
            "desc" : {
               "da" : "Denne gang er vi med til Rally Monte-Carlo Historique. Vi f\u00f8lger de 7 Danske teams under hele l\u00f8bet fra Pre-Starten i Assens p\u00e5 Fyn til m\u00e5lrampen i Monaco."
            },
            "date" : "2018",
            "new" : null
         },
         {
            "stop" : "1522594500",
            "category" : {
               "en" : [
                  "series",
                  "Series"
               ]
            },
            "episodeNum" : {
               "xmltv_ns" : ". 1/12 .",
               "onscreen" : "Afsnit 2 af 12"
            },
            "channel" : "tv2nord.dk",
            "date" : "2015",
            "new" : null,
            "title" : {
               "da" : "Vild mad"
            },
            "start" : "1522592700",
            "desc" : {
               "da" : "Et anderledes madprogram hvor kokken Michael Eriksen og v\u00e6rt Marie Frank Mitchell er rykket ud under \u00e5ben himmel for at lave mad over \u00e5ben ild. R\u00e5varerne kommer fra vildmarken og bliver til l\u00e6kre retter, som man sagtens selv kan lave derhjemme."
            }
         },
         {
            "category" : {
               "en" : [
                  "series",
                  "Series"
               ]
            },
            "title" : {
               "da" : "Naturperler - Svalen"
            },
            "start" : "1522594500",
            "desc" : {
               "da" : "I programmet \"Naturperler\" kommer vi t\u00e6t p\u00e5 Danmarks dyr og natur. Dette program handler om svaler. De er fantastiske flyvere. De tilbringer vinteren i Sydafrika, s\u00e5 hvert \u00e5r skal de flyve over 20.000 km, bare for at overvintre. Rejsen g\u00e5r over \u00f8rkener og over Europas h\u00f8jeste bjerge - men ikke alle n\u00e5r frem. Tilrettel\u00e6ggelse: Bo Skelmose"
            },
            "channel" : "tv2nord.dk",
            "stop" : "1522596300",
            "new" : null
         },
         {
            "new" : null,
            "desc" : {
               "da" : "Kirkemagasin fra Nord- , Midt- og Vestjylland."
            },
            "start" : "1522596300",
            "title" : {
               "da" : "Vorherre Bevares"
            },
            "stop" : "1522598100",
            "channel" : "tv2nord.dk",
            "episodeNum" : {
               "xmltv_ns" : ". 3/11 .",
               "onscreen" : "Afsnit 4 af 11"
            },
            "category" : {
               "en" : [
                  "series",
                  "Series"
               ]
            }
         },
         {
            "new" : null,
            "stop" : "1522599900",
            "start" : "1522598100",
            "desc" : {
               "da" : "Fangstgaranti titlen forpligter - det handler ganske enkelt om at hive en masse forskellige fisk i land. I hvert afsnit tager programmets v\u00e6rt Morten Stamm Mikkelsen p\u00e5 fisketur med en lystfisker, der er ekspert i at fange dagens fisk. Det kan v\u00e6re alt fra hav\u00f8rreder og laks, over gedder, st\u00f8r og karper til kulmuler og store torsk."
            },
            "channel" : "tv2nord.dk",
            "category" : {
               "en" : [
                  "series",
                  "Series"
               ]
            },
            "title" : {
               "da" : "Fangstgaranti"
            }
         },
         {
            "channel" : "tv2nord.dk",
            "desc" : {
               "da" : "Nyhedsopdatering fra TV2/NORD - f\u00f8lg med p\u00e5 tv2nord.dk"
            },
            "start" : "1522599900",
            "title" : {
               "da" : "Nyheder 1820 April"
            },
            "category" : {
               "en" : [
                  "series",
                  "Series"
               ]
            },
            "new" : null,
            "stop" : "1522600200"
         },
         {
            "title" : {
               "da" : "Vild med dyr"
            },
            "desc" : {
               "da" : "Anna Louise Tran\u00e6s Didriksen kommer helt t\u00e6t p\u00e5 dyrene sammen med de personer, der til daglig arbejder med dem."
            },
            "start" : "1522600200",
            "new" : null,
            "credits" : {
               "presenter" : [
                  {
                     "name" : "Anne Louise T. Didriksen"
                  }
               ]
            },
            "category" : {
               "en" : [
                  "series",
                  "Series"
               ]
            },
            "channel" : "tv2nord.dk",
            "episodeNum" : {
               "xmltv_ns" : ". 84/97 .",
               "onscreen" : "Afsnit 85 af 97"
            },
            "stop" : "1522602000"
         },
         {
            "channel" : "tv2nord.dk",
            "desc" : {
               "da" : "Josefine Ottesen er en succesrig forfatter, men nu er hun ogs\u00e5 ejer af et forsamlingshus. Hun har nemlig k\u00f8bt en bygning i sin hjemby, svendborg, og den 31. marts \u00e5bner hun Svendborg Forsamlingshus. Det fort\u00e6ller hun Annemette Voss om i dag, n\u00e5r hun er medv\u00e6rt. M\u00f8d ogs\u00e5 de driftige folk i \u00e5rets landsby i Midtjylland, Sall, som lige nu er i gang med at bygge et whiskydestilleri."
            },
            "start" : "1522602000",
            "category" : {
               "en" : [
                  "series",
                  "Series"
               ]
            },
            "title" : {
               "da" : "S\u00e5danmark"
            },
            "new" : null,
            "stop" : "1522603800"
         },
         {
            "title" : {
               "da" : "Nordjylland Live"
            },
            "category" : {
               "en" : [
                  "series",
                  "Series"
               ]
            },
            "channel" : "tv2nord.dk",
            "start" : "1522603800",
            "desc" : {
               "da" : "Direkte fra studiet i Aabybro byder vi p\u00e5 levende fjernsyn med n\u00e6rv\u00e6rende nordjyske reportager, aktuelle g\u00e6ster i studiet, dagens vigtigste historier fra Nordjylland og aktuelle emner til debat."
            },
            "stop" : "1522604700",
            "new" : null
         },
         {
            "start" : "1522604700",
            "desc" : {
               "da" : "Man kan sige det samme p\u00e5 mange forskellige m\u00e5der her i Danmark. Kom med i krinkelkrogene i det danske sprog, n\u00e5r Jylland og \u00f8erne t\u00f8rner sammen i en dyst, hvor det handler om at forvirre hinanden og hj\u00e6lpe hinanden gennem junglen af lokale udtryk, slang og dialekt. De tre jyder rapper Jonny Hefty, foredragsholder Gitte Hornsh\u00f8j og l\u00e6rer Anette Karkov k\u00e6mper for hovedlandet. P\u00e5 \u00f8-holdet samles det verbale skyts af musiker Jason Svendstorp , studerende Daniel Mieritz og Entertainer Bjarne Kure. V\u00e6rt er Sussi R\u00f8mer Rasmussen."
            },
            "channel" : "tv2nord.dk",
            "title" : {
               "da" : "Sprogblomster - det sk\u00f8nne danske sprog"
            },
            "category" : {
               "en" : [
                  "series",
                  "Series"
               ]
            },
            "new" : null,
            "stop" : "1522606500"
         },
         {
            "start" : "1522606500",
            "desc" : {
               "da" : "Det eneste vi er sikre p\u00e5, n\u00e5r vi bliver f\u00f8dt er, at vi skal d\u00f8. Alligevel er d\u00f8den et tabu for mange. Men hvorfor er det egentlig s\u00e5dan? En fotograf og en journalist flyttede ind p\u00e5 Hospice Vendsyssel i 7 d\u00f8gn for at f\u00f8lge livet - og d\u00f8den - p\u00e5 n\u00e6rmeste hold. Det er der kommet 4 unikke programmer ud af. Tilrettel\u00e6ggelse: Jesper Bradsted og S\u00f8ren Broust Hansen"
            },
            "title" : {
               "da" : "7 d\u00f8gn p\u00e5 hospice"
            },
            "new" : null,
            "episodeNum" : {
               "xmltv_ns" : ". 2/4 .",
               "onscreen" : "Afsnit 3 af 4"
            },
            "channel" : "tv2nord.dk",
            "category" : {
               "en" : [
                  "series",
                  "Series"
               ]
            },
            "stop" : "1522608300"
         },
         {
            "start" : "1522608300",
            "desc" : {
               "da" : "I Appetit bes\u00f8ger vi nyere spisesteder i hele regionen, der t\u00e6nker nyt i forhold til koncept og mad. I dagens udgave af Appetit er vi taget til fiskeribyen Hanstholm ved Thy. Det er de tre venner Morten, Mai og Louise, der st\u00e5r bag Hanstholm Madbar. Begge valgte at rykke teltp\u00e6lene op og flytte fra K\u00f8benhavn og Djursland til Thy for at kaste sig ud i projektet. Stedet er uformelt og har hygge og samv\u00e6r i h\u00f8js\u00e6det og de tre ejer er altid klar p\u00e5 et glas portvin og en sludder med g\u00e6sterne. Tilrettel\u00e6ggelse: Helene Gottschalk Dahl og Johnni Isaksen"
            },
            "title" : {
               "da" : "Appetit"
            },
            "new" : null,
            "channel" : "tv2nord.dk",
            "episodeNum" : {
               "onscreen" : "Afsnit 6 af 8",
               "xmltv_ns" : ". 5/8 ."
            },
            "category" : {
               "en" : [
                  "series",
                  "Series"
               ]
            },
            "stop" : "1522610100"
         },
         {
            "desc" : {
               "da" : "Det eneste vi er sikre p\u00e5, n\u00e5r vi bliver f\u00f8dt er, at vi skal d\u00f8. Alligevel er d\u00f8den et tabu for mange. Men hvorfor er det egentlig s\u00e5dan? En fotograf og en journalist flyttede ind p\u00e5 Hospice Vendsyssel i 7 d\u00f8gn for at f\u00f8lge livet - og d\u00f8den - p\u00e5 n\u00e6rmeste hold. Det er der kommet 4 unikke programmer ud af. Tilrettel\u00e6ggelse: Jesper Bradsted og S\u00f8ren Broust Hansen"
            },
            "start" : "1522610100",
            "title" : {
               "da" : "7 d\u00f8gn p\u00e5 hospice"
            },
            "new" : null,
            "channel" : "tv2nord.dk",
            "episodeNum" : {
               "xmltv_ns" : ". 0/4 .",
               "onscreen" : "Afsnit 1 af 4"
            },
            "category" : {
               "en" : [
                  "series",
                  "Series"
               ]
            },
            "stop" : "1522611900"
         },
         {
            "date" : "2017",
            "new" : null,
            "title" : {
               "da" : "Mit k\u00e6reste eje - B\u00e6kmarksbro"
            },
            "start" : "1522611900",
            "desc" : {
               "da" : "Danmark bugner af sjove gamle ting og smukke antikviteter, og de fleste seere har et eller andet klenodie st\u00e5ende fremme til pynt eller gemt godt af vejen i kommodeskuffen. Nogle af dem kan I se i programmet \"Mit k\u00e6reste eje\". Hver gang dukker der effekter op, som viser sig at v\u00e6re meget mere - eller meget mindre - v\u00e6rd, end ejerne forventer. Auktionsleder Hans J\u00f8rgen Eriksen har vurderet gamle ting i over 25 \u00e5r. Han er uddannet advokat, men valgte i 1998 udelukkende at hellige sig sin virksomhed Holstebro Auktioner. Sammen med v\u00e6rt Anne Moulvad tager han rundt i landsdelen og ser p\u00e5 gamle ting og sager. Denne gang er de p\u00e5 bes\u00f8g p\u00e5 B\u00e6kmarksbro Pleje- og Daghjem, hvor de bl.a. ser p\u00e5 en B & O Radio fra 1939, en ko med kalv i porcel\u00e6n og en Petromaxlygte."
            },
            "stop" : "1522613700",
            "category" : {
               "en" : [
                  "series",
                  "Series"
               ]
            },
            "channel" : "tv2nord.dk",
            "episodeNum" : {
               "onscreen" : "Afsnit 1 af 3",
               "xmltv_ns" : ". 0/3 ."
            }
         },
         {
            "stop" : "1522615500",
            "new" : null,
            "category" : {
               "en" : [
                  "series",
                  "Series"
               ]
            },
            "title" : {
               "da" : "Sprogblomster - det sk\u00f8nne danske sprog"
            },
            "channel" : "tv2nord.dk",
            "desc" : {
               "da" : "Man kan sige det samme p\u00e5 mange forskellige m\u00e5der her i Danmark. Kom med i krinkelkrogene i det danske sprog, n\u00e5r Jylland og \u00f8erne t\u00f8rner sammen i en dyst, hvor det handler om at forvirre hinanden og hj\u00e6lpe hinanden gennem junglen af lokale udtryk, slang og dialekt. De tre jyder rapper Jonny Hefty, foredragsholder Gitte Hornsh\u00f8j og l\u00e6rer Anette Karkov k\u00e6mper for hovedlandet. P\u00e5 \u00f8-holdet samles det verbale skyts af musiker Jason Svendstorp , studerende Daniel Mieritz og Entertainer Bjarne Kure. V\u00e6rt er Sussi R\u00f8mer Rasmussen."
            },
            "start" : "1522613700"
         },
         {
            "new" : null,
            "title" : {
               "da" : "Livet p\u00e5 landet - M\u00e6h, siger det lille lam"
            },
            "desc" : {
               "da" : "V\u00e6rt Maria Bernhard f\u00f8lger hverdagen og arbejdslivet p\u00e5 fire af regionens landbrug."
            },
            "start" : "1522615500",
            "stop" : "1522617300",
            "category" : {
               "en" : [
                  "series",
                  "Series"
               ]
            },
            "credits" : {
               "presenter" : [
                  {
                     "name" : "Maria Bernhard"
                  }
               ]
            },
            "channel" : "tv2nord.dk"
         },
         {
            "category" : {
               "en" : [
                  "series",
                  "Series"
               ]
            },
            "title" : {
               "da" : "S\u00e5danmark"
            },
            "channel" : "tv2nord.dk",
            "start" : "1522617300",
            "desc" : {
               "da" : "Dagens medv\u00e6rt i S\u00e5danmark er en af landets mest l\u00e6ste bloggere, Mascha Vang. Hun solgte i efter\u00e5ret sit bloggernetv\u00e6rk og nyder at have langt mindre ansvar og mere tid til sin datter. M\u00f8d ogs\u00e5 Klitm\u00f8llers Casper Steinfath inden hans lange tur p\u00e5 stand up paddle-br\u00e6t over Skagerak. Dagens v\u00e6rt: Annemette Voss."
            },
            "stop" : "1522618980",
            "new" : null
         },
         {
            "title" : {
               "da" : "Nyheder fra tv2nord.dk"
            },
            "category" : {
               "en" : [
                  "series",
                  "Series"
               ]
            },
            "start" : "1522618980",
            "channel" : "tv2nord.dk",
            "stop" : "1522673700",
            "new" : null
         }
      ]
   }
}
