{
   "jsontv" : {
      "programme" : [
         {
            "stop" : "1531468800",
            "title" : {
               "da" : "En god start - bev\u00e6gelse og stegt laks"
            },
            "channel" : "tveast.dk",
            "new" : null,
            "credits" : {
               "presenter" : [
                  {
                     "name" : "Katja Kafling"
                  }
               ]
            },
            "start" : "1531467000",
            "desc" : {
               "da" : "<br><br> Stegt laks med dildsm\u00f8rsauce og ris<br><br> 4 personer<br><br> 4 laksefileter \u00e1 cirka 150 gr.<br> Salt & peber<br> Sm\u00f8r eller olie til stegning<br> 200 g friske spinatblade (frosset kan ogs\u00e5 bruges, husk at presse v\u00e6den ud af spinaten)<br> 1 tsk. sm\u00f8r<br> 1/2 bundt dild<br><br> Dildsm\u00f8r:<br> 1/4 dl hvidvinseddike (alm. eddike kan i en sn\u00e6ver vending ogs\u00e5 bruges)<br> 1 tsk. grovkornet sennep<br> 1 tsk. honning<br> 1 dl hvidvin <br> 30 g sm\u00f8r<br> 1/2 bundt dild<br> Salt & peber<br><br> Tilbeh\u00f8r:<br> Ris (her kan ogs\u00e5 bruges vilde ris, hvis man vil \u00f8ge sundheden en anelse)<br><br> S\u00e5dan g\u00f8r du:<br> Risen s\u00e6ttes over og koge.<br> Sk\u00e6r laksen ud i stykker p\u00e5 4-6 cm. alt efter \u00f8nske. Krydr laksefileterne med salt og peber og steg dem ca. 4 minutter p\u00e5 hver side i sm\u00f8r ved j\u00e6vn varme. Skyl spinaten og damp den i sm\u00f8r til den falder sammen. Bland spinaten med grofthakket dild og smag til med salt og peber.<br> Kog hvidvinseddike, sennep, honning og hvidvin ind til det halve. Tag gryden af varmen, pisk sm\u00f8r og finthakket dild i saucen og smag til med salt og peber. Serv\u00e9r saucen til den stegte laks p\u00e5 en bund af dampet spinat.<br><br> Opskriften er fra uddannelsesinstitutionen ZBC i Vordingborg."
            },
            "category" : {
               "en" : [
                  "series",
                  "Series"
               ]
            }
         },
         {
            "episodeNum" : {
               "xmltv_ns" : ". 9/12 .",
               "onscreen" : "Afsnit 10 af 12"
            },
            "desc" : {
               "da" : "Genbrug, teaktr\u00e6 og palisander er popul\u00e6rt som aldrig f\u00f8r. Vi er vilde med m\u00f8bler, der langtfra er nye, og det har to kvinder i Viborg taget til sig. Vi kigger Maja og Majken over skulderen, n\u00e5r de g\u00e5r p\u00e5 ting-jagt."
            },
            "category" : {
               "en" : [
                  "series",
                  "Series"
               ]
            },
            "stop" : "1531470600",
            "start" : "1531468800",
            "new" : null,
            "title" : {
               "da" : "Maja & Majken - Formidable fund"
            },
            "channel" : "tveast.dk"
         },
         {
            "stop" : "1531472100",
            "title" : {
               "da" : "Klar til Sommersjov - \u00c5bningsdag"
            },
            "channel" : "tveast.dk",
            "credits" : {
               "presenter" : [
                  {
                     "name" : "Ulrik Westphal"
                  }
               ]
            },
            "new" : null,
            "start" : "1531470600",
            "desc" : {
               "da" : "De to sj\u00e6llandske forlystelsesparker, Bonbonland og Sommerland Sj\u00e6lland, er omdrejningspunktet i en reportageserie p\u00e5 TV \u00d8st. Men der skal meget til at holde en moderne forlystelsespark k\u00f8rende og forventningerne til s\u00e6sonen 2016 er store. S\u00e5 det bliver en travl s\u00e6son i de to parker."
            },
            "category" : {
               "en" : [
                  "series",
                  "Series"
               ]
            }
         },
         {
            "channel" : "tveast.dk",
            "title" : {
               "da" : "Vild mad"
            },
            "start" : "1531472100",
            "new" : null,
            "stop" : "1531473900",
            "category" : {
               "en" : [
                  "series",
                  "Series"
               ]
            },
            "episodeNum" : {
               "onscreen" : "Afsnit 5 af 15",
               "xmltv_ns" : ". 4/15 ."
            },
            "desc" : {
               "da" : "Et anderledes madprogram hvor Kok Michael Eriksen og v\u00e6rt Marie Frank Mitchell er rykket ud under \u00e5ben himmel for at lave mad over \u00e5ben ild. R\u00e5varerne kommer fra vildmarken og bliver til l\u00e6kre retter, som man sagtens selv kan lave derhjemme."
            }
         },
         {
            "stop" : "1531475700",
            "new" : null,
            "start" : "1531473900",
            "desc" : {
               "da" : "Hvad\u00a0laver\u00a0en\u00a0brandmand\u00a0egentligt?\u00a0Og\u00a0hvor\u00a0sv\u00e6rt\u00a0er\u00a0det,\u00a0for\u00a0en\u00a0u\u00f8vet\u00a0at\u00a0overtage\u00a0arbejdsopgaverne?\u00a0I\u00a0vores\u00a0serie,\u00a0Bornholm\u00a0Knokler,\u00a0tager\u00a0vi\u00a0ud\u00a0og\u00a0pr\u00f8ver\u00a0mange\u00a0forskellige\u00a0jobs\u00a0---\u00a0og\u00a0finder\u00a0ud\u00a0af,\u00a0hvad\u00a0de\u00a0indeb\u00e6rer."
            },
            "category" : {
               "en" : [
                  "series",
                  "Series"
               ]
            },
            "title" : {
               "da" : "Bornholm knokler - Brandinspekt\u00f8r"
            },
            "channel" : "tveast.dk"
         },
         {
            "stop" : "1531477500",
            "desc" : {
               "da" : "Det er blevet sommerferie i Danmark, og det er tydeligt at opleve i denne udgave af S\u00e5danmark. M\u00f8d frivillige ved sommerens arrangementer, f\u00e5r historien om dengang, vi slet ikke holdt sommerferie i Danmark og kom med til biltr\u00e6f i Thisted, hvor duften af br\u00e6ndt gummi er s\u00e5 sk\u00f8n, at arrang\u00f8ren ville \u00f8nske, han kunne f\u00e5 den som deo. I studiet er v\u00e6rt Annemette Voss Fridthjof og medv\u00e6rt Thomas Funding."
            },
            "category" : {
               "en" : [
                  "series",
                  "Series"
               ]
            },
            "title" : {
               "da" : "S\u00e5danmark"
            },
            "channel" : "tveast.dk",
            "new" : null,
            "start" : "1531475700"
         },
         {
            "category" : {
               "en" : [
                  "series",
                  "Series"
               ]
            },
            "desc" : {
               "da" : "V\u00e6rt: Sille Roulund og vurderingsekspert: Steffen Dinesen. Det bliver n\u00e6rmest til undervisning i hvad kinesernene foretr\u00e6kker indefor rav. Et helt glad med rav i forskellige farver og st\u00f8rrelser gl\u00e6der vurderingschefen. Stykkerne er fundet p\u00e5 Ulvshale for mange \u00e5r siden."
            },
            "start" : "1531477500",
            "new" : null,
            "credits" : {
               "presenter" : [
                  {
                     "name" : "Sille Roulund"
                  }
               ]
            },
            "title" : {
               "da" : "Mit K\u00e6reste Eje - Bjergbestiger"
            },
            "channel" : "tveast.dk",
            "stop" : "1531479300"
         },
         {
            "stop" : "1531482000",
            "start" : "1531479300",
            "new" : null,
            "channel" : "tveast.dk",
            "category" : {
               "en" : [
                  "series",
                  "Series"
               ]
            },
            "desc" : {
               "da" : "Strikkedysten er optaget i for\u00e5ret p\u00e5 Gram Slot. I v\u00e6rtsrollen ses igen Koushi Radhakrishnan, og dommerne er de samme som i de tidligere to s\u00e6soner: Christel Seyfarth og Vithard Villumsen."
            },
            "title" : {
               "da" : "Den Store Strikkedyst 1"
            }
         },
         {
            "new" : null,
            "start" : "1531482000",
            "channel" : "tveast.dk",
            "category" : {
               "en" : [
                  "series",
                  "Series"
               ]
            },
            "desc" : {
               "da" : "Produceret i 2014."
            },
            "title" : {
               "da" : "Derudaf! - fisk, vaders og Zoo"
            },
            "stop" : "1531483800"
         },
         {
            "stop" : "1531485600",
            "title" : {
               "da" : "Ud i det bl\u00e5 - Frederiksdal"
            },
            "channel" : "tveast.dk",
            "new" : null,
            "credits" : {
               "presenter" : [
                  {
                     "name" : "Sille Roulund"
                  }
               ]
            },
            "start" : "1531483800",
            "desc" : {
               "da" : "En smule regn skr\u00e6mmer ikke b\u00f8rnene i skovb\u00f8rnehaven i Frederiksdal skoven. Og en hel del regn skr\u00e6mmer dem slet ikke. S\u00e5 bliver mudderkagerne bare nemmere at lave. Dagens rute g\u00e5r b\u00e5de p\u00e5 Frederiksdal Strandrute og p\u00e5 skovruten. Og i skoven er der ogs\u00e5 rig mulighed for at finde svampe for tiden. Men det er ikke alle, der kan spises, s\u00e5 det er en god id\u00e9 enten at tage en med, der kender til svampene eller tage med p\u00e5 en af de mange svampeture, der er i \u00f8jeblikket. Kirseb\u00e6rene p\u00e5 Frederiksdal Gods har f\u00e5et for meget vand. De har simpelt hen optaget s\u00e5 meget, at mange af dem er revnet og s\u00e5 r\u00e5dner de lige s\u00e5 stille. N\u00e5r det sker kan de ikke bruge til kirseb\u00e6rvin, som godset ellers har fremstillet siden 2006.Heldigvis er det ikke hele h\u00f8sten, der er \u00f8delagt. Men godsejeren h\u00e5ber p\u00e5 en bedre h\u00f8st til n\u00e6ste \u00e5r, s\u00e5 produktionen kan holdes igang."
            },
            "category" : {
               "en" : [
                  "series",
                  "Series"
               ]
            }
         },
         {
            "desc" : {
               "da" : "Fej\u00f8 har et B\u00f8rnehus, hvor alle b\u00f8rnene er samlet. Og n\u00e5r de stopper i b\u00f8rnehave kan de g\u00e5 ind af d\u00f8ren ved siden af og begynde i skole. Her kan de g\u00e5 til fjerde klasse. Og det er netop hvad b\u00f8rnene i familien fra \u00d8lstykke skal. Familien flyttede til \u00f8en for et par \u00e5r siden for at f\u00e5 b\u00e5de job, familie og fritid til at h\u00e6nge bedre sammen. Og det er lykkes for dem i stor stil. Her er der ingen planer om at flytte igen."
            },
            "category" : {
               "en" : [
                  "series",
                  "Series"
               ]
            },
            "new" : null,
            "credits" : {
               "presenter" : [
                  {
                     "name" : "Mads Gudiksen"
                  }
               ]
            },
            "start" : "1531485600",
            "title" : {
               "da" : "\u00d8-liv: Fej\u00f8"
            },
            "channel" : "tveast.dk",
            "stop" : "1531487400"
         },
         {
            "stop" : "1531489200",
            "new" : null,
            "start" : "1531487400",
            "credits" : {
               "presenter" : [
                  {
                     "name" : "Mads Gudiksen"
                  }
               ]
            },
            "title" : {
               "da" : "Zoo og Safari - Ulvefodring"
            },
            "channel" : "tveast.dk",
            "desc" : {
               "da" : "Mads Gudiksen bes\u00f8ger nogle af regionens zoo og dyreparker. Her stifter Mads bekendtskab med hidsige krokodiller, k\u00e6rlige aber, talende fugle, farlige tigre, k\u00e6mpe n\u00e6sehorn og sparkende kameler. Og Mads giver gerne en h\u00e5nd med, hvis girafferne skal fodres, en slange skal flyttes eller melormene skal pr\u00f8vespises."
            },
            "category" : {
               "en" : [
                  "series",
                  "Series"
               ]
            }
         },
         {
            "stop" : "1531490100",
            "category" : {
               "en" : [
                  "series",
                  "Series"
               ]
            },
            "desc" : {
               "da" : "I 8 afsnit \u00e5bner TV2Nord d\u00f8rene op til et helt nyt og sp\u00e6ndende tv-eksperiment. Her skal vores testdeltager sammen med seeren igennem en noget anderledes og gr\u00e6nseoverskridende rejse. Den anerkendte singer-songwriter Laura Mo har sagt ja til at deltage i projektet, hvor hun i l\u00f8bet af 4-dage, uden en krone p\u00e5 lommen skal klare sig igennem livet p\u00e5 landevejen langt v\u00e6k fra hendes normale og trygge omgivelser. P\u00e5 rejsen m\u00f8der hun den tidligere vagabond Svend Erik Rasmussen, der har over 25 \u00e5rs erfaring med livet p\u00e5 landevejen. Hos ham, vil hun st\u00e5 i mesterl\u00e6re, og han vil coache hende i livet - levet under \u00e5ben himmel, hvor der er offentlig adgang. Programr\u00e6kken er en dokumentarisk rejse, hvor vi kommer ud p\u00e5 kanten og hvor der bliver eventyr, blod, sved og t\u00e5rer. Tilrettel\u00e6ggelse: Niels Meredin og Anders Hestbek Genudsendelse fra 2014"
            },
            "channel" : "tveast.dk",
            "title" : {
               "da" : "Laura og Vagabonden"
            },
            "start" : "1531489200",
            "new" : null
         },
         {
            "desc" : {
               "da" : "Tag med p\u00e5 familiehotellet, der ligger direkte ned til \u00d8sters\u00f8en og Stevns Klint. Her blander en sjov familie sig med g\u00e6ster, der cykler, vandrer og sv\u00f8mmer i den majest\u00e6tiske natur."
            },
            "category" : {
               "en" : [
                  "series",
                  "Series"
               ]
            },
            "start" : "1531490100",
            "new" : null,
            "credits" : {
               "presenter" : [
                  {
                     "name" : "Katja Kafling"
                  }
               ]
            },
            "channel" : "tveast.dk",
            "title" : {
               "da" : "Hotel med stil - R\u00f8dvig Kro og Badehotel"
            },
            "stop" : "1531491900"
         },
         {
            "category" : {
               "en" : [
                  "series",
                  "Series"
               ]
            },
            "channel" : "tveast.dk",
            "desc" : {
               "da" : "De bedste historier fra hele Danmark og dagens medv\u00e6rt:"
            },
            "title" : {
               "da" : "S\u00e5danmark"
            },
            "start" : "1531491900",
            "new" : null,
            "stop" : "1531493700"
         },
         {
            "start" : "1531493700",
            "new" : null,
            "channel" : "tveast.dk",
            "title" : {
               "da" : "Guden\u00e5en - en rejse p\u00e5 floden"
            },
            "stop" : "1531495500",
            "episodeNum" : {
               "xmltv_ns" : ". 5/12 .",
               "onscreen" : "Afsnit 6 af 12"
            },
            "desc" : {
               "da" : "Naturvejleder Karsten Hansen snyder for det h\u00e5rde arbejde med padlen i den gamle tr\u00e6kano og f\u00e5r et lift i en solb\u00e5d hele vejen til Himmelbjerget. Der er stadig langt til havet men alligevel tid til at bes\u00f8ge en masse glade, legende b\u00f8rn p\u00e5 lejr ved Juls\u00f8. Tilrettel\u00e6ggelse: Karsten Hansen"
            },
            "category" : {
               "en" : [
                  "series",
                  "Series"
               ]
            }
         },
         {
            "category" : {
               "en" : [
                  "series",
                  "Series"
               ]
            },
            "desc" : {
               "da" : "Sille og Erik tr\u00e6kker igen i arbejdst\u00f8jet. Bev\u00e6bnet med b\u00e5de besk\u00e6resaks og havehandsker viser de, hvad der er godt at g\u00f8re i haven netop nu. I Ud I Haven f\u00f8lger vi \u00e5rets gang i Silles have, men der bliver ogs\u00e5 tid til bes\u00f8g hos andre haveejere. Hver uge er der gode r\u00e5d til hvordan du passer buske, planter og drivhus."
            },
            "title" : {
               "da" : "Ud i Haven - Kolonihaver"
            },
            "channel" : "tveast.dk",
            "credits" : {
               "presenter" : [
                  {
                     "name" : "Sille Roulund"
                  }
               ]
            },
            "new" : null,
            "start" : "1531495500",
            "stop" : "1531497300"
         },
         {
            "stop" : "1531499100",
            "new" : null,
            "start" : "1531497300",
            "desc" : {
               "da" : "UDEFRA er programserien hvor vi sender programmer fra de andre regioner. Her bes\u00f8ger vi Bornholm der knokler."
            },
            "category" : {
               "en" : [
                  "series",
                  "Series"
               ]
            },
            "title" : {
               "da" : "Bornholm knokler - L\u00e6rer p\u00e5 HF"
            },
            "channel" : "tveast.dk"
         },
         {
            "stop" : "1531499400",
            "desc" : {
               "da" : "Produceret af TV \u00d8ST."
            },
            "category" : {
               "en" : [
                  "series",
                  "Series"
               ]
            },
            "channel" : "tveast.dk",
            "title" : {
               "da" : "Nyheder"
            },
            "new" : null,
            "start" : "1531499100"
         },
         {
            "title" : {
               "da" : "Vild mad"
            },
            "channel" : "tveast.dk",
            "start" : "1531499400",
            "new" : null,
            "stop" : "1531501200",
            "episodeNum" : {
               "xmltv_ns" : ". 5/15 .",
               "onscreen" : "Afsnit 6 af 15"
            },
            "category" : {
               "en" : [
                  "series",
                  "Series"
               ]
            },
            "desc" : {
               "da" : "Et anderledes madprogram hvor Kok Michael Eriksen og v\u00e6rt Marie Frank Mitchell er rykket ud under \u00e5ben himmel for at lave mad over \u00e5ben ild. R\u00e5varerne kommer fra vildmarken og bliver til l\u00e6kre retter, som man sagtens selv kan lave derhjemme."
            }
         },
         {
            "desc" : {
               "da" : "Danmark bugner af sjove gamle ting og smukke antikviteter, og de fleste seere har et eller andet klenodie st\u00e5ende fremme til pynt eller gemt godt af vejen i kommodeskuffen. Nogle af dem kan du se i Mit k\u00e6reste Eje. Der er fine ting til vurdering p\u00e5 Skjoldn\u00e6sholm. Et bryllupskrus med familiehistorie, der g\u00e5r 300 \u00e5r tilbage, f\u00e5r en h\u00f8j vurdering med p\u00e5 vejen. Den f\u00f8rste ting, der begejstrer Steffen Dinesen er dog langt fra Dansk - men helt fra Kina."
            },
            "category" : {
               "en" : [
                  "series",
                  "Series"
               ]
            },
            "stop" : "1531503000",
            "new" : null,
            "credits" : {
               "presenter" : [
                  {
                     "name" : "Sille Roulund"
                  }
               ]
            },
            "start" : "1531501200",
            "channel" : "tveast.dk",
            "title" : {
               "da" : "Mit K\u00e6reste Eje - Kinesisk Bronze"
            }
         },
         {
            "stop" : "1531504200",
            "desc" : {
               "da" : "Produceret af TV \u00d8St."
            },
            "category" : {
               "en" : [
                  "series",
                  "Series"
               ]
            },
            "channel" : "tveast.dk",
            "title" : {
               "da" : "Nyheder"
            },
            "new" : null,
            "start" : "1531503000"
         },
         {
            "stop" : "1531505700",
            "start" : "1531504200",
            "new" : null,
            "credits" : {
               "presenter" : [
                  {
                     "name" : "Mads Gudiksen"
                  }
               ]
            },
            "channel" : "tveast.dk",
            "title" : {
               "da" : "Mad med Gods i - Sporvejsfrokost"
            },
            "desc" : {
               "da" : "Mads Gudiksen og David Jensin bes\u00f8ger regionens sp\u00e6ndende godser."
            },
            "category" : {
               "en" : [
                  "series",
                  "Series"
               ]
            }
         },
         {
            "category" : {
               "en" : [
                  "series",
                  "Series"
               ]
            },
            "desc" : {
               "da" : "De bedste historier fra hele Danmark og dagens medv\u00e6rt:"
            },
            "title" : {
               "da" : "S\u00e5danmark"
            },
            "channel" : "tveast.dk",
            "start" : "1531505700",
            "new" : null,
            "stop" : "1531507500"
         },
         {
            "stop" : "1531509300",
            "start" : "1531507500",
            "new" : null,
            "desc" : {
               "da" : "Produceret af TV Syd."
            },
            "category" : {
               "en" : [
                  "series",
                  "Series"
               ]
            },
            "channel" : "tveast.dk",
            "title" : {
               "da" : "\u00c5rstidens Spisekammer 17 - k\u00e5l"
            }
         },
         {
            "category" : {
               "en" : [
                  "series",
                  "Series"
               ]
            },
            "desc" : {
               "da" : "Produceret af TV \u00d8St."
            },
            "channel" : "tveast.dk",
            "title" : {
               "da" : "Nyheder"
            },
            "new" : null,
            "start" : "1531509300",
            "stop" : "1531510500"
         },
         {
            "desc" : {
               "da" : "Mads Gudiksen og David Jensin bes\u00f8ger regionens sp\u00e6ndende godser."
            },
            "category" : {
               "en" : [
                  "series",
                  "Series"
               ]
            },
            "stop" : "1531512300",
            "title" : {
               "da" : "Mad med Gods i - Sporvejsfrokost"
            },
            "channel" : "tveast.dk",
            "new" : null,
            "credits" : {
               "presenter" : [
                  {
                     "name" : "Mads Gudiksen"
                  }
               ]
            },
            "start" : "1531510500"
         },
         {
            "new" : null,
            "start" : "1531512300",
            "credits" : {
               "presenter" : [
                  {
                     "name" : "Ulrik Westphal"
                  },
                  {
                     "name" : "S\u00f8ren Larsen"
                  }
               ]
            },
            "channel" : "tveast.dk",
            "title" : {
               "da" : "Under Overfladen - Sj\u00e6llands Odde"
            },
            "stop" : "1531513800",
            "desc" : {
               "da" : "Under Overfladen dykker vi ned og oplever rigdommen og livet under vand."
            },
            "category" : {
               "en" : [
                  "series",
                  "Series"
               ]
            }
         },
         {
            "stop" : "1531515600",
            "new" : null,
            "start" : "1531513800",
            "credits" : {
               "presenter" : [
                  {
                     "name" : "Katja Kafling"
                  }
               ]
            },
            "title" : {
               "da" : "Turist for en dag i Slagelse"
            },
            "channel" : "tveast.dk",
            "desc" : {
               "da" : "Turist for en dag. Katja Kafling har sat sig for at unders\u00f8ge nogle af de mange ting, der foreg\u00e5r i byerne i vores region. Hun drager ud som turist i 16 byer og finder de bedste spisesteder, de bedste is, museer og underholdning for b\u00e5de b\u00f8rn og voksne. I Turist for en dag f\u00e5r du et bud p\u00e5, hvad du kan lave i fx Slagelse, Nakskov eller N\u00e6stved, hvis du vil have en sjov fridag."
            },
            "category" : {
               "en" : [
                  "series",
                  "Series"
               ]
            }
         },
         {
            "category" : {
               "en" : [
                  "series",
                  "Series"
               ]
            },
            "desc" : {
               "da" : "De bedste historier fra hele Danmark og dagens medv\u00e6rt:"
            },
            "channel" : "tveast.dk",
            "title" : {
               "da" : "S\u00e5danmark"
            },
            "start" : "1531515600",
            "new" : null,
            "stop" : "1531517400"
         },
         {
            "start" : "1531517400",
            "new" : null,
            "category" : {
               "en" : [
                  "series",
                  "Series"
               ]
            },
            "desc" : {
               "da" : "Produceret af TV Syd."
            },
            "title" : {
               "da" : "\u00c5rstidens Spisekammer 17 - k\u00e5l"
            },
            "channel" : "tveast.dk",
            "stop" : "1531553400"
         }
      ]
   }
}
